ormlambda/__init__.py
ormlambda/caster/__init__.py
ormlambda/caster/base_caster.py
ormlambda/caster/caster.py
ormlambda/caster/interfaces/ICaster.py
ormlambda/caster/interfaces/__init__.py
ormlambda/common/__init__.py
ormlambda/common/constants.py
ormlambda/common/enums/__init__.py
ormlambda/common/enums/condition_types.py
ormlambda/common/enums/join_type.py
ormlambda/common/enums/order_type.py
ormlambda/common/enums/union_type.py
ormlambda/common/errors/__init__.py
ormlambda/common/global_checker.py
ormlambda/common/interfaces/IJoinSelector.py
ormlambda/common/interfaces/IQueryCommand.py
ormlambda/common/interfaces/__init__.py
ormlambda/dialects/__init__.py
ormlambda/dialects/default/__init__.py
ormlambda/dialects/default/base.py
ormlambda/dialects/mysql/__init__.py
ormlambda/dialects/mysql/base.py
ormlambda/dialects/mysql/caster/__init__.py
ormlambda/dialects/mysql/caster/caster.py
ormlambda/dialects/mysql/caster/types/__init__.py
ormlambda/dialects/mysql/caster/types/boolean.py
ormlambda/dialects/mysql/caster/types/bytes.py
ormlambda/dialects/mysql/caster/types/date.py
ormlambda/dialects/mysql/caster/types/datetime.py
ormlambda/dialects/mysql/caster/types/decimal.py
ormlambda/dialects/mysql/caster/types/float.py
ormlambda/dialects/mysql/caster/types/int.py
ormlambda/dialects/mysql/caster/types/iterable.py
ormlambda/dialects/mysql/caster/types/json.py
ormlambda/dialects/mysql/caster/types/none.py
ormlambda/dialects/mysql/caster/types/point.py
ormlambda/dialects/mysql/caster/types/string.py
ormlambda/dialects/mysql/clauses/ST_AsText.py
ormlambda/dialects/mysql/clauses/ST_Contains.py
ormlambda/dialects/mysql/clauses/__init__.py
ormlambda/dialects/mysql/mysqlconnector.py
ormlambda/dialects/mysql/repository/__init__.py
ormlambda/dialects/mysql/repository/pool_types.py
ormlambda/dialects/mysql/repository/repository.py
ormlambda/dialects/mysql/types.py
ormlambda/dialects/sqlite/__init__.py
ormlambda/dialects/sqlite/base.py
ormlambda/dialects/sqlite/pysqlite.py
ormlambda-4.4.4.dist-info/AUTHORS
ormlambda-4.4.4.dist-info/LICENSE
ormlambda-4.4.4.dist-info/METADATA
ormlambda-4.4.4.dist-info/WHEEL
ormlambda-4.4.4.dist-info/RECORD
