Metadata-Version: 2.1
Name: ormlambda
Version: 4.4.4
Summary: ORM designed to interact with the database (currently with MySQL) using lambda functions and nested functions
Author: p-hzamora
Author-email: p.hzamora@icloud.com
Requires-Python: >=3.12,<4.0
Classifier: Programming Language :: Python :: 3
Classifier: Programming Language :: Python :: 3.12
Requires-Dist: mysql-connector-python (>=9.0.0,<10.0.0)
Requires-Dist: shapely (>=2.0.6,<3.0.0)
